llmreader/__init__.py
llmreader/inject.py
llmreader-0.2.8.dist-info/LICENSE
llmreader-0.2.8.dist-info/METADATA
llmreader-0.2.8.dist-info/WHEEL
llmreader-0.2.8.dist-info/top_level.txt
llmreader-0.2.8.dist-info/RECORD
