Metadata-Version: 2.1
Name: llmreader
Version: 0.2.8
Summary: Intercept OpenAI inputs
Author: Ethan Hou
Author-email: ethanfhou10@gmail.com
Classifier: Programming Language :: Python :: 3
Classifier: License :: OSI Approved :: MIT License
Classifier: Operating System :: OS Independent
License-File: LICENSE
Requires-Dist: openai
